AUTHORS.rst
LICENSE
README.rst
setup.cfg
setup.py
solidskksg.egg-info/PKG-INFO
solidskksg.egg-info/SOURCES.txt
solidskksg.egg-info/dependency_links.txt
solidskksg.egg-info/entry_points.txt
solidskksg.egg-info/requires.txt
solidskksg.egg-info/top_level.txt
solidspy/__init__.py
solidspy/__main__.py
solidspy/assemutil.py
solidspy/blochutil.py
solidspy/femutil.py
solidspy/gaussutil.py
solidspy/postprocesor.py
solidspy/preprocesor.py
solidspy/solids_GUI.py
solidspy/solutil.py
solidspy/uelutil.py
tests/test_assemutil.py
tests/test_bloch.py
tests/test_femutil.py
tests/test_gaussutil.py
tests/test_integration.py
tests/test_postprocesor.py
tests/test_preprocesor.py
tests/test_solutil.py
tests/test_uelutil.py