Metadata-Version: 2.1
Name: solidskksg
Version: 0.5
Summary: A simple Finite Element program
Home-page: https://github.com/AppliedMechanics-EAFIT/SolidsPy
Author: Nicolas Guarin-Zapata <nguarinz@eafit.edu.co>, Juan Gomez <jgomezc1@eafit.edu.co>
Author-email: nguarinz@eafit.edu.co
License: MIT
Keywords: finite-elements fem scientific-computing
Classifier: Development Status :: 4 - Beta
Classifier: Intended Audience :: Education
Classifier: Topic :: Scientific/Engineering
Classifier: License :: OSI Approved :: MIT License
Classifier: Programming Language :: Python :: 3
License-File: LICENSE
License-File: AUTHORS.rst
Requires-Dist: numpy
Requires-Dist: scipy
Requires-Dist: matplotlib
Requires-Dist: easygui
Requires-Dist: meshio==3.0
